deddiag_loader/__init__.py
deddiag_loader/__main__.py
deddiag_loader/_cache.py
deddiag_loader/_cli.py
deddiag_loader/_db.py
deddiag_loader/_formatter.py
deddiag_loader/_loader.py
deddiag_loader/utils.py
deddiag_loader-0.1.7.dist-info/LICENSE
deddiag_loader-0.1.7.dist-info/METADATA
deddiag_loader-0.1.7.dist-info/WHEEL
deddiag_loader-0.1.7.dist-info/top_level.txt
deddiag_loader-0.1.7.dist-info/RECORD
