Metadata-Version: 2.1
Name: deddiag-loader
Version: 0.1.7
Summary: Loader for DEDDIAG, a Domestic Energy Demand Dataset of Individual Appliances Germany
Home-page: https://github.com/DEDDIAG/deddiag-loader
Author: Marc Wenninger
Author-email: pypi@walwe.de
License: UNKNOWN
Platform: UNKNOWN
Classifier: Programming Language :: Python :: 3
Classifier: License :: OSI Approved :: MIT License
Classifier: Operating System :: OS Independent
Requires-Python: >=3.6
License-File: LICENSE
Requires-Dist: pandas
Requires-Dist: sqlalchemy
Requires-Dist: psycopg2
Requires-Dist: click
